[{"title":"Taanach","link":"/en/wol/d/r1/lp-e/1200004289"},{"title":"Taanath-shiloh","link":"/en/wol/d/r1/lp-e/1200004290"},{"title":"Tabbaoth","link":"/en/wol/d/r1/lp-e/1200004291"},{"title":"Tabbath","link":"/en/wol/d/r1/lp-e/1200004292"},{"title":"Tabeel","link":"/en/wol/d/r1/lp-e/1200004293"},{"title":"Taberah","link":"/en/wol/d/r1/lp-e/1200004294"},{"title":"Tabernacle","link":"/en/wol/d/r1/lp-e/1200004295"},{"title":"Tabitha","link":"/en/wol/d/r1/lp-e/1200004296"},{"title":"Tableland","link":"/en/wol/d/r1/lp-e/1200004297"},{"title":"Tabor","link":"/en/wol/d/r1/lp-e/1200004298"},{"title":"Tabrimmon","link":"/en/wol/d/r1/lp-e/1200004299"},{"title":"Tadmor","link":"/en/wol/d/r1/lp-e/1200004300"},{"title":"Tahan","link":"/en/wol/d/r1/lp-e/1200004301"},{"title":"Tahash","link":"/en/wol/d/r1/lp-e/1200004302"},{"title":"Tahath","link":"/en/wol/d/r1/lp-e/1200004303"},{"title":"Tahchemonite","link":"/en/wol/d/r1/lp-e/1200004304"},{"title":"Tahpanes","link":"/en/wol/d/r1/lp-e/1200004305"},{"title":"Tahpenes","link":"/en/wol/d/r1/lp-e/1200004306"},{"title":"Tahrea","link":"/en/wol/d/r1/lp-e/1200004307"},{"title":"Tahtim-hodshi","link":"/en/wol/d/r1/lp-e/1200004308"},{"title":"Talent","link":"/en/wol/d/r1/lp-e/1200004309"},{"title":"Talitha Cumi","link":"/en/wol/d/r1/lp-e/1200004310"},{"title":"Talmai","link":"/en/wol/d/r1/lp-e/1200004311"},{"title":"Talmon","link":"/en/wol/d/r1/lp-e/1200004312"},{"title":"Tamar","link":"/en/wol/d/r1/lp-e/1200004313"},{"title":"Tamarisk","link":"/en/wol/d/r1/lp-e/1200004314"},{"title":"Tambourine","link":"/en/wol/d/r1/lp-e/1200004315"},{"title":"Tammuz, I","link":"/en/wol/d/r1/lp-e/1200004316"},{"title":"Tammuz, II","link":"/en/wol/d/r1/lp-e/1200004317"},{"title":"Tanhumeth","link":"/en/wol/d/r1/lp-e/1200004318"},{"title":"Tanner","link":"/en/wol/d/r1/lp-e/1200004319"},{"title":"Taphath","link":"/en/wol/d/r1/lp-e/1200004320"},{"title":"Tappuah","link":"/en/wol/d/r1/lp-e/1200004321"},{"title":"Tar","link":"/en/wol/d/r1/lp-e/1200004322"},{"title":"Taralah","link":"/en/wol/d/r1/lp-e/1200004323"},{"title":"Tarea","link":"/en/wol/d/r1/lp-e/1200004324"},{"title":"Tarshish","link":"/en/wol/d/r1/lp-e/1200004325"},{"title":"Tarsus","link":"/en/wol/d/r1/lp-e/1200004326"},{"title":"Tartak","link":"/en/wol/d/r1/lp-e/1200004327"},{"title":"Tartan","link":"/en/wol/d/r1/lp-e/1200004328"},{"title":"Tartarus","link":"/en/wol/d/r1/lp-e/1200004329"},{"title":"Tattenai","link":"/en/wol/d/r1/lp-e/1200004330"},{"title":"Tattoo","link":"/en/wol/d/r1/lp-e/1200004331"},{"title":"Taw","link":"/en/wol/d/r1/lp-e/1200004332"},{"title":"Taxation","link":"/en/wol/d/r1/lp-e/1200004333"},{"title":"Tax Collector","link":"/en/wol/d/r1/lp-e/1200004334"},{"title":"Teacher, Teaching","link":"/en/wol/d/r1/lp-e/1200004335"},{"title":"Tebah","link":"/en/wol/d/r1/lp-e/1200004336"},{"title":"Tebaliah","link":"/en/wol/d/r1/lp-e/1200004337"},{"title":"Tebeth","link":"/en/wol/d/r1/lp-e/1200004338"},{"title":"Teeth","link":"/en/wol/d/r1/lp-e/1200004339"},{"title":"Tehaphnehes","link":"/en/wol/d/r1/lp-e/1200004340"},{"title":"Tehinnah","link":"/en/wol/d/r1/lp-e/1200004341"},{"title":"Tehth","link":"/en/wol/d/r1/lp-e/1200004342"},{"title":"Tekel","link":"/en/wol/d/r1/lp-e/1200004343"},{"title":"Tekoa","link":"/en/wol/d/r1/lp-e/1200004344"},{"title":"Tekoite","link":"/en/wol/d/r1/lp-e/1200004345"},{"title":"Tel-abib","link":"/en/wol/d/r1/lp-e/1200004346"},{"title":"Telah","link":"/en/wol/d/r1/lp-e/1200004347"},{"title":"Telaim","link":"/en/wol/d/r1/lp-e/1200004348"},{"title":"Telam","link":"/en/wol/d/r1/lp-e/1200004349"},{"title":"Tel-assar","link":"/en/wol/d/r1/lp-e/1200004350"},{"title":"Telem","link":"/en/wol/d/r1/lp-e/1200004351"},{"title":"Tel-harsha","link":"/en/wol/d/r1/lp-e/1200004352"},{"title":"Tel-melah","link":"/en/wol/d/r1/lp-e/1200004353"},{"title":"Tema","link":"/en/wol/d/r1/lp-e/1200004354"},{"title":"Temah","link":"/en/wol/d/r1/lp-e/1200004355"},{"title":"Teman","link":"/en/wol/d/r1/lp-e/1200004356"},{"title":"Temanite","link":"/en/wol/d/r1/lp-e/1200004357"},{"title":"Temeni","link":"/en/wol/d/r1/lp-e/1200004358"},{"title":"Temple","link":"/en/wol/d/r1/lp-e/1200004359"},{"title":"Ten","link":"/en/wol/d/r1/lp-e/1200004360"},{"title":"Ten Commandments","link":"/en/wol/d/r1/lp-e/1200004361"},{"title":"Tent","link":"/en/wol/d/r1/lp-e/1200004362"},{"title":"Tenth Part","link":"/en/wol/d/r1/lp-e/1200004363"},{"title":"Tentmaker","link":"/en/wol/d/r1/lp-e/1200004364"},{"title":"Tent of Meeting","link":"/en/wol/d/r1/lp-e/1200004365"},{"title":"Tent of the Testimony","link":"/en/wol/d/r1/lp-e/1200004366"},{"title":"Ten Words","link":"/en/wol/d/r1/lp-e/1200004367"},{"title":"Terah","link":"/en/wol/d/r1/lp-e/1200004368"},{"title":"Teraphim","link":"/en/wol/d/r1/lp-e/1200004369"},{"title":"Teresh","link":"/en/wol/d/r1/lp-e/1200004370"},{"title":"Tertius","link":"/en/wol/d/r1/lp-e/1200004371"},{"title":"Tertullus","link":"/en/wol/d/r1/lp-e/1200004372"},{"title":"Testicles","link":"/en/wol/d/r1/lp-e/1200004373"},{"title":"Thaddaeus","link":"/en/wol/d/r1/lp-e/1200004374"},{"title":"Theater","link":"/en/wol/d/r1/lp-e/1200004375"},{"title":"Thebez","link":"/en/wol/d/r1/lp-e/1200004376"},{"title":"Theophilus","link":"/en/wol/d/r1/lp-e/1200004377"},{"title":"Thessalonians, Letters to the","link":"/en/wol/d/r1/lp-e/1200004378"},{"title":"Thessalonica","link":"/en/wol/d/r1/lp-e/1200004379"},{"title":"Theudas","link":"/en/wol/d/r1/lp-e/1200004380"},{"title":"Thief","link":"/en/wol/d/r1/lp-e/1200004381"},{"title":"Thigh","link":"/en/wol/d/r1/lp-e/1200004382"},{"title":"Thinking Ability","link":"/en/wol/d/r1/lp-e/1200004383"},{"title":"Thistle","link":"/en/wol/d/r1/lp-e/1200004384"},{"title":"Thomas","link":"/en/wol/d/r1/lp-e/1200004385"},{"title":"Thorn","link":"/en/wol/d/r1/lp-e/1200004386"},{"title":"Thornbush","link":"/en/wol/d/r1/lp-e/1200004387"},{"title":"Three Taverns","link":"/en/wol/d/r1/lp-e/1200004388"},{"title":"Threshing","link":"/en/wol/d/r1/lp-e/1200004389"},{"title":"Throat","link":"/en/wol/d/r1/lp-e/1200004390"},{"title":"Throne","link":"/en/wol/d/r1/lp-e/1200004391"},{"title":"Thumb","link":"/en/wol/d/r1/lp-e/1200004392"},{"title":"Thummim","link":"/en/wol/d/r1/lp-e/1200004393"},{"title":"Thunder","link":"/en/wol/d/r1/lp-e/1200004394"},{"title":"Thunder, Sons of","link":"/en/wol/d/r1/lp-e/1200004395"},{"title":"Thyatira","link":"/en/wol/d/r1/lp-e/1200004396"},{"title":"Tiberias","link":"/en/wol/d/r1/lp-e/1200004397"},{"title":"Tiberius","link":"/en/wol/d/r1/lp-e/1200004398"},{"title":"Tibhath","link":"/en/wol/d/r1/lp-e/1200004399"},{"title":"Tibni","link":"/en/wol/d/r1/lp-e/1200004400"},{"title":"Tidal","link":"/en/wol/d/r1/lp-e/1200004401"},{"title":"Tiglath-pileser (III)","link":"/en/wol/d/r1/lp-e/1200004402"},{"title":"Tikvah","link":"/en/wol/d/r1/lp-e/1200004403"},{"title":"Tilgath-pilneser","link":"/en/wol/d/r1/lp-e/1200004404"},{"title":"Tilon","link":"/en/wol/d/r1/lp-e/1200004405"},{"title":"Timaeus","link":"/en/wol/d/r1/lp-e/1200004406"},{"title":"Time(s)","link":"/en/wol/d/r1/lp-e/1200004407"},{"title":"Time Indefinite","link":"/en/wol/d/r1/lp-e/1200004408"},{"title":"Time of the End","link":"/en/wol/d/r1/lp-e/1200004409"},{"title":"Timna","link":"/en/wol/d/r1/lp-e/1200004410"},{"title":"Timnah","link":"/en/wol/d/r1/lp-e/1200004411"},{"title":"Timnath-heres","link":"/en/wol/d/r1/lp-e/1200004412"},{"title":"Timnath-serah","link":"/en/wol/d/r1/lp-e/1200004413"},{"title":"Timnite","link":"/en/wol/d/r1/lp-e/1200004414"},{"title":"Timon","link":"/en/wol/d/r1/lp-e/1200004415"},{"title":"Timothy","link":"/en/wol/d/r1/lp-e/1200004416"},{"title":"Timothy, Letters to","link":"/en/wol/d/r1/lp-e/1200004417"},{"title":"Tin","link":"/en/wol/d/r1/lp-e/1200004418"},{"title":"Tiphsah","link":"/en/wol/d/r1/lp-e/1200004419"},{"title":"Tiras","link":"/en/wol/d/r1/lp-e/1200004420"},{"title":"Tirathites","link":"/en/wol/d/r1/lp-e/1200004421"},{"title":"Tirhakah","link":"/en/wol/d/r1/lp-e/1200004422"},{"title":"Tirhanah","link":"/en/wol/d/r1/lp-e/1200004423"},{"title":"Tiria","link":"/en/wol/d/r1/lp-e/1200004424"},{"title":"Tirshatha","link":"/en/wol/d/r1/lp-e/1200004425"},{"title":"Tirzah","link":"/en/wol/d/r1/lp-e/1200004426"},{"title":"Tishbite","link":"/en/wol/d/r1/lp-e/1200004427"},{"title":"Tishri","link":"/en/wol/d/r1/lp-e/1200004428"},{"title":"Tithe","link":"/en/wol/d/r1/lp-e/1200004429"},{"title":"Titius Justus","link":"/en/wol/d/r1/lp-e/1200004430"},{"title":"Titus","link":"/en/wol/d/r1/lp-e/1200004431"},{"title":"Titus, Letter to","link":"/en/wol/d/r1/lp-e/1200004432"},{"title":"Tizite","link":"/en/wol/d/r1/lp-e/1200004433"},{"title":"Toah","link":"/en/wol/d/r1/lp-e/1200004434"},{"title":"Tob","link":"/en/wol/d/r1/lp-e/1200004435"},{"title":"Tob-adonijah","link":"/en/wol/d/r1/lp-e/1200004436"},{"title":"Tobiah","link":"/en/wol/d/r1/lp-e/1200004437"},{"title":"Tobijah","link":"/en/wol/d/r1/lp-e/1200004438"},{"title":"Tochen","link":"/en/wol/d/r1/lp-e/1200004439"},{"title":"Toe","link":"/en/wol/d/r1/lp-e/1200004440"},{"title":"Togarmah","link":"/en/wol/d/r1/lp-e/1200004441"},{"title":"Tohu","link":"/en/wol/d/r1/lp-e/1200004442"},{"title":"Toi","link":"/en/wol/d/r1/lp-e/1200004443"},{"title":"Tola","link":"/en/wol/d/r1/lp-e/1200004444"},{"title":"Tolad","link":"/en/wol/d/r1/lp-e/1200004445"},{"title":"Tolaites","link":"/en/wol/d/r1/lp-e/1200004446"},{"title":"Tomb","link":"/en/wol/d/r1/lp-e/1200004447"},{"title":"Tongue","link":"/en/wol/d/r1/lp-e/1200004448"},{"title":"Tongues, Speaking in","link":"/en/wol/d/r1/lp-e/1200004449"},{"title":"Topaz","link":"/en/wol/d/r1/lp-e/1200004450"},{"title":"Tophel","link":"/en/wol/d/r1/lp-e/1200004451"},{"title":"Topheth","link":"/en/wol/d/r1/lp-e/1200004452"},{"title":"Torch","link":"/en/wol/d/r1/lp-e/1200004453"},{"title":"Torment","link":"/en/wol/d/r1/lp-e/1200004454"},{"title":"Torrent Valley","link":"/en/wol/d/r1/lp-e/1200004455"},{"title":"Torture Stake","link":"/en/wol/d/r1/lp-e/1200004456"},{"title":"Tou","link":"/en/wol/d/r1/lp-e/1200004457"},{"title":"Tow","link":"/en/wol/d/r1/lp-e/1200004458"},{"title":"Tower","link":"/en/wol/d/r1/lp-e/1200004459"},{"title":"Tower of Babel","link":"/en/wol/d/r1/lp-e/1200004460"},{"title":"Town","link":"/en/wol/d/r1/lp-e/1200004461"},{"title":"Trachonitis","link":"/en/wol/d/r1/lp-e/1200004462"},{"title":"Tradition","link":"/en/wol/d/r1/lp-e/1200004463"},{"title":"Traitor","link":"/en/wol/d/r1/lp-e/1200004464"},{"title":"Trance","link":"/en/wol/d/r1/lp-e/1200004465"},{"title":"Transfiguration","link":"/en/wol/d/r1/lp-e/1200004466"},{"title":"Transgression","link":"/en/wol/d/r1/lp-e/1200004467"},{"title":"Translator","link":"/en/wol/d/r1/lp-e/1200004468"},{"title":"Transportation","link":"/en/wol/d/r1/lp-e/1200004469"},{"title":"Trap","link":"/en/wol/d/r1/lp-e/1200004470"},{"title":"Treasury","link":"/en/wol/d/r1/lp-e/1200004471"},{"title":"Trees","link":"/en/wol/d/r1/lp-e/1200004472"},{"title":"Trespass","link":"/en/wol/d/r1/lp-e/1200004473"},{"title":"Trial","link":"/en/wol/d/r1/lp-e/1200004474"},{"title":"Tribe","link":"/en/wol/d/r1/lp-e/1200004475"},{"title":"Tribulation","link":"/en/wol/d/r1/lp-e/1200004476"},{"title":"Tribunal","link":"/en/wol/d/r1/lp-e/1200004477"},{"title":"Tribute","link":"/en/wol/d/r1/lp-e/1200004478"},{"title":"Triumphal Procession","link":"/en/wol/d/r1/lp-e/1200004479"},{"title":"Troas","link":"/en/wol/d/r1/lp-e/1200004480"},{"title":"Trophimus","link":"/en/wol/d/r1/lp-e/1200004481"},{"title":"Trumpet","link":"/en/wol/d/r1/lp-e/1200004482"},{"title":"Truth","link":"/en/wol/d/r1/lp-e/1200004483"},{"title":"Tryphaena","link":"/en/wol/d/r1/lp-e/1200004484"},{"title":"Tryphosa","link":"/en/wol/d/r1/lp-e/1200004485"},{"title":"Tsadheh","link":"/en/wol/d/r1/lp-e/1200004486"},{"title":"Tsohar","link":"/en/wol/d/r1/lp-e/1200004487"},{"title":"Tubal","link":"/en/wol/d/r1/lp-e/1200004488"},{"title":"Tubal-cain","link":"/en/wol/d/r1/lp-e/1200004489"},{"title":"Turban","link":"/en/wol/d/r1/lp-e/1200004490"},{"title":"Turning Around","link":"/en/wol/d/r1/lp-e/1200004491"},{"title":"Turquoise","link":"/en/wol/d/r1/lp-e/1200004492"},{"title":"Turtledove","link":"/en/wol/d/r1/lp-e/1200004493"},{"title":"Tutor","link":"/en/wol/d/r1/lp-e/1200004494"},{"title":"Twelve, The","link":"/en/wol/d/r1/lp-e/1200004495"},{"title":"Tychicus","link":"/en/wol/d/r1/lp-e/1200004496"},{"title":"Tyrannus","link":"/en/wol/d/r1/lp-e/1200004497"},{"title":"Tyre","link":"/en/wol/d/r1/lp-e/1200004498"},{"title":"Tyrian","link":"/en/wol/d/r1/lp-e/1200004499"}]